bigowl/__init__.py
bigowl/analyzer.py
bigowl/complexity/__init__.py
bigowl/complexity/space_complexity.py
bigowl/complexity/time_complexity.py
bigowl/parser/__init__.py
bigowl/parser/ast_parser.py
bigowl/parser/code_parser.py
bigowl/utils/__init__.py
bigowl/utils/helpers.py
bigowl-0.1.0.dist-info/licenses/LICENSE
tests/__init__.py
tests/test_analyzer.py
tests/test_space_complexity.py
tests/test_time_complexity.py
bigowl-0.1.0.dist-info/METADATA
bigowl-0.1.0.dist-info/WHEEL
bigowl-0.1.0.dist-info/top_level.txt
bigowl-0.1.0.dist-info/RECORD
