Metadata-Version: 2.4
Name: BigOwl
Version: 0.1.0
Summary: An intelligent time and space complexity analyzer for Python code.
Home-page: https://github.com/CrazAr374/BigOwl
Author: Atharva Rahate
Author-email: atharvarahate374@example.com
License: MIT
Classifier: Programming Language :: Python :: 3
Classifier: Operating System :: OS Independent
Requires-Python: >=3.6
License-File: LICENSE
Requires-Dist: asttokens
Requires-Dist: networkx
Dynamic: author
Dynamic: author-email
Dynamic: classifier
Dynamic: description
Dynamic: description-content-type
Dynamic: home-page
Dynamic: license
Dynamic: license-file
Dynamic: requires-dist
Dynamic: requires-python
Dynamic: summary
